pygbase8s/__init__.py
pygbase8s/cluster.py
pygbase8s/cm.py
pygbase8s/dblog.py
pygbase8s/dbspace.py
pygbase8s/driver_manager.py
pygbase8s/env.py
pygbase8s/instance.py
pygbase8s/machine.py
pygbase8s/onconfig.py
pygbase8s/product.py
pygbase8s/server.py
pygbase8s/server_pool.py
pygbase8s/sqlhosts.py
pygbase8s/ssh_session.py
pygbase8s-1.3.0.dist-info/LICENSE
pygbase8s-1.3.0.dist-info/METADATA
pygbase8s-1.3.0.dist-info/WHEEL
pygbase8s-1.3.0.dist-info/top_level.txt
pygbase8s-1.3.0.dist-info/RECORD
