Metadata-Version: 2.1
Name: pygbase8s
Version: 1.3.0
Summary: A package for GBase 8s database installation and cluster setup.
Home-page: https://gitee.com/momo3507/pygbase8s.git
Author: wangwei
Author-email: wangwei3@gbase.cn
License: MIT
Platform: UNKNOWN
Classifier: License :: OSI Approved :: MIT License
Classifier: Programming Language :: Python :: 3
Classifier: Programming Language :: Python :: 3.8
Classifier: Programming Language :: Python :: Implementation :: CPython
Classifier: Programming Language :: Python :: Implementation :: PyPy
Requires-Python: >=3.7.0
License-File: LICENSE
Requires-Dist: paramiko
